logos/__init__.py
logos/api.py
logos/utils.py
logos-0.3.dist-info/METADATA
logos-0.3.dist-info/WHEEL
logos-0.3.dist-info/top_level.txt
logos-0.3.dist-info/RECORD
